pokelance/__init__.py
pokelance/cache/__init__.py
pokelance/cache/cache.py
pokelance/cache/cache_manager.py
pokelance/client.py
pokelance/constants.py
pokelance/exceptions.py
pokelance/ext/__init__.py
pokelance/ext/_base.py
pokelance/ext/berry.py
pokelance/ext/contest.py
pokelance/ext/encounter.py
pokelance/ext/evolution.py
pokelance/ext/game.py
pokelance/ext/item.py
pokelance/ext/location.py
pokelance/ext/machine.py
pokelance/ext/move.py
pokelance/ext/pokemon.py
pokelance/http/__init__.py
pokelance/http/endpoints.py
pokelance/languages.py
pokelance/logger.py
pokelance/models/__init__.py
pokelance/models/_base.py
pokelance/models/abstract/__init__.py
pokelance/models/abstract/berry.py
pokelance/models/abstract/contest.py
pokelance/models/abstract/encounter.py
pokelance/models/abstract/evolution.py
pokelance/models/abstract/game.py
pokelance/models/abstract/item.py
pokelance/models/abstract/location.py
pokelance/models/abstract/machine.py
pokelance/models/abstract/move.py
pokelance/models/abstract/pokemon.py
pokelance/models/abstract/utils/__init__.py
pokelance/models/abstract/utils/berries.py
pokelance/models/abstract/utils/contests.py
pokelance/models/abstract/utils/evolutions.py
pokelance/models/abstract/utils/games.py
pokelance/models/abstract/utils/items.py
pokelance/models/abstract/utils/locations.py
pokelance/models/abstract/utils/moves.py
pokelance/models/abstract/utils/pokemons.py
pokelance/models/common/__init__.py
pokelance/models/common/models.py
pokelance/models/common/resources.py
pokelance/py.typed
pokelance/utils.py
pokelance-0.2.10.dist-info/LICENSE
pokelance-0.2.10.dist-info/METADATA
pokelance-0.2.10.dist-info/WHEEL
pokelance-0.2.10.dist-info/RECORD
