Metadata-Version: 2.3
Name: pokelance
Version: 0.2.10
Summary: A flexible and easy to use pokemon library.
License: MIT
Author: FallenDeity
Author-email: 61227305+FallenDeity@users.noreply.github.com
Requires-Python: >=3.8,<4.0
Classifier: License :: OSI Approved :: MIT License
Classifier: Programming Language :: Python :: 3
Classifier: Programming Language :: Python :: 3.8
Classifier: Programming Language :: Python :: 3.9
Classifier: Programming Language :: Python :: 3.10
Classifier: Programming Language :: Python :: 3.11
Classifier: Programming Language :: Python :: 3.12
Classifier: Programming Language :: Python :: 3.13
Requires-Dist: aiofiles (>=23.1.0,<24.0.0)
Requires-Dist: aiohttp (>=3.8.3,<4.0.0)
Requires-Dist: attrs (>=23.1.0,<24.0.0)
Requires-Dist: types-aiofiles (>=23.1.0.1,<24.0.0.0)
